<?xml version="1.0" encoding="UTF-8" standalone="no"?>
<cardDataBase>
    <sets>
        <set>
            <name>
                <![CDATA[15th Anniversary]]>
            </name>
            <code>
                <![CDATA[15A]]>
            </code>
            <is_promo>
                <![CDATA[true]]>
            </is_promo>
            <date>
                <![CDATA[00/0000]]>
            </date>
        </set>
        <set>
            <code>
                <![CDATA[AER]]>
            </code>
            <is_promo>
                <![CDATA[false]]>
            </is_promo>
            <date>
                <![CDATA[01/2017]]>
            </date>
            <name>
                <![CDATA[Aether Revolt]]>
            </name>
        </set>
        <set>
            <code>
                <![CDATA[ARB]]>
            </code>
            <is_promo>
                <![CDATA[false]]>
            </is_promo>
            <date>
                <![CDATA[04/2009]]>
            </date>
            <name>
                <![CDATA[Alara Reborn]]>
            </name>
        </set>
        <set>
            <is_promo>
                <![CDATA[false]]>
            </is_promo>
            <code>
                <![CDATA[ALL]]>
            </code>
            <date>
                <![CDATA[06/1996]]>
            </date>
            <name>
                <![CDATA[Alliances]]>
            </name>
        </set>
        <set>
            <is_promo>
                <![CDATA[false]]>
            </is_promo>
            <code>
                <![CDATA[AKH]]>
            </code>
            <date>
                <![CDATA[04/2017]]>
            </date>
            <name>
                <![CDATA[Amonkhet]]>
            </name>
        </set>
        <set>
            <is_promo>
                <![CDATA[true]]>
            </is_promo>
            <code>
                <![CDATA[ATH]]>
            </code>
            <date>
                <![CDATA[11/1998]]>
            </date>
            <name>
                <![CDATA[Anthologies]]>
            </name>
        </set>
        <set>
            <is_promo>
                <![CDATA[false]]>
            </is_promo>
            <code>
                <![CDATA[ATQ]]>
            </code>
            <date>
                <![CDATA[04/1994]]>
            </date>
            <name>
                <![CDATA[Antiquities]]>
            </name>
        </set>
        <set>
            <is_promo>
                <![CDATA[false]]>
            </is_promo>
            <date>
                <![CDATA[05/2001]]>
            </date>
            <code>
                <![CDATA[APC]]>
            </code>
            <name>
                <![CDATA[Apocalypse]]>
            </name>
        </set>
        <set>
            <is_promo>
                <![CDATA[false]]>
            </is_promo>
            <date>
                <![CDATA[12/1993]]>
            </date>
            <code>
                <![CDATA[ARN]]>
            </code>
            <name>
                <![CDATA[Arabian Nights]]>
            </name>
        </set>
        <set>
            <is_promo>
                <![CDATA[true]]>
            </is_promo>
            <date>
                <![CDATA[06/2010]]>
            </date>
            <code>
                <![CDATA[ARC]]>
            </code>
            <name>
                <![CDATA[Archenemy]]>
            </name>
        </set>
        <set>
            <is_promo>
                <![CDATA[true]]>
            </is_promo>
            <date>
                <![CDATA[06/2010]]>
            </date>
            <code>
                <![CDATA[ARCS]]>
            </code>
            <name>
                <![CDATA[Archenemy "Schemes"]]>
            </name>
        </set>
        <set>
            <is_promo>
                <![CDATA[true]]>
            </is_promo>
            <date>
                <![CDATA[06/2017]]>
            </date>
            <code>
                <![CDATA[E01]]>
            </code>
            <name>
                <![CDATA[Archenemy: Nicol Bolas]]>
            </name>
        </set>
        <set>
            <is_promo>
                <![CDATA[true]]>
            </is_promo>
            <date>
                <![CDATA[06/2017]]>
            </date>
            <code>
                <![CDATA[E01S]]>
            </code>
            <name>
                <![CDATA[Archenemy: Nicol Bolas "Schemes"]]>
            </name>
        </set>
        <set>
            <is_promo>
                <![CDATA[true]]>
            </is_promo>
            <date>
                <![CDATA[00/0000]]>
            </date>
            <code>
                <![CDATA[ARENA]]>
            </code>
            <name>
                <![CDATA[Arena League]]>
            </name>
        </set>
        <set>
            <is_promo>
                <![CDATA[true]]>
            </is_promo>
            <date>
                <![CDATA[00/0000]]>
            </date>
            <code>
                <![CDATA[APAC]]>
            </code>
            <name>
                <![CDATA[Asia Pacific Land Program]]>
            </name>
        </set>
        <set>
            <date>
                <![CDATA[05/2012]]>
            </date>
            <code>
                <![CDATA[AVR]]>
            </code>
            <is_promo>
                <![CDATA[false]]>
            </is_promo>
            <name>
                <![CDATA[Avacyn Restored]]>
            </name>
        </set>
        <set>
            <date>
                <![CDATA[10/2015]]>
            </date>
            <code>
                <![CDATA[BFZ]]>
            </code>
            <is_promo>
                <![CDATA[false]]>
            </is_promo>
            <name>
                <![CDATA[Battle for Zendikar]]>
            </name>
        </set>
        <set>
            <date>
                <![CDATA[11/1999]]>
            </date>
            <code>
                <![CDATA[BRB]]>
            </code>
            <is_promo>
                <![CDATA[true]]>
            </is_promo>
            <name>
                <![CDATA[Battle Royale Box Set]]>
            </name>
        </set>
        <set>
            <date>
                <![CDATA[02/2014]]>
            </date>
            <code>
                <![CDATA[TBTH]]>
            </code>
            <is_promo>
                <![CDATA[true]]>
            </is_promo>
            <name>
                <![CDATA[Battle the Horde]]>
            </name>
        </set>
        <set>
            <date>
                <![CDATA[06/2018]]>
            </date>
            <code>
                <![CDATA[BBD]]>
            </code>
            <is_promo>
                <![CDATA[false]]>
            </is_promo>
            <name>
                <![CDATA[Battlebond]]>
            </name>
        </set>
        <set>
            <date>
                <![CDATA[12/2000]]>
            </date>
            <code>
                <![CDATA[BTD]]>
            </code>
            <is_promo>
                <![CDATA[true]]>
            </is_promo>
            <name>
                <![CDATA[Beatdown Box Set]]>
            </name>
        </set>
        <set>
            <date>
                <![CDATA[01/2005]]>
            </date>
            <code>
                <![CDATA[BOK]]>
            </code>
            <is_promo>
                <![CDATA[false]]>
            </is_promo>
            <name>
                <![CDATA[Betrayers of Kamigawa]]>
            </name>
        </set>
        <set>
            <date>
                <![CDATA[02/2014]]>
            </date>
            <code>
                <![CDATA[BNG]]>
            </code>
            <is_promo>
                <![CDATA[false]]>
            </is_promo>
            <name>
                <![CDATA[Born of the Gods]]>
            </name>
        </set>
        <set>
            <date>
                <![CDATA[00/0000]]>
            </date>
            <code>
                <![CDATA[UQC]]>
            </code>
            <is_promo>
                <![CDATA[true]]>
            </is_promo>
            <name>
                <![CDATA[Celebration Cards]]>
            </name>
        </set>
        <set>
            <date>
                <![CDATA[09/2004]]>
            </date>
            <code>
                <![CDATA[CHK]]>
            </code>
            <is_promo>
                <![CDATA[false]]>
            </is_promo>
            <name>
                <![CDATA[Champions of Kamigawa]]>
            </name>
        </set>
        <set>
            <date>
                <![CDATA[00/0000]]>
            </date>
            <code>
                <![CDATA[CHA]]>
            </code>
            <is_promo>
                <![CDATA[true]]>
            </is_promo>
            <name>
                <![CDATA[Champs]]>
            </name>
        </set>
        <set>
            <date>
                <![CDATA[07/1995]]>
            </date>
            <code>
                <![CDATA[CHR]]>
            </code>
            <is_promo>
                <![CDATA[false]]>
            </is_promo>
            <name>
                <![CDATA[Chronicles]]>
            </name>
        </set>
        <set>
            <date>
                <![CDATA[06/2006]]>
            </date>
            <code>
                <![CDATA[CSP]]>
            </code>
            <is_promo>
                <![CDATA[false]]>
            </is_promo>
            <name>
                <![CDATA[Coldsnap]]>
            </name>
        </set>
        <set>
            <date>
                <![CDATA[06/2006]]>
            </date>
            <code>
                <![CDATA[CST]]>
            </code>
            <is_promo>
                <![CDATA[true]]>
            </is_promo>
            <name>
                <![CDATA[Coldsnap Theme Decks]]>
            </name>
        </set>
        <set>
            <date>
                <![CDATA[06/2011]]>
            </date>
            <code>
                <![CDATA[CMD]]>
            </code>
            <is_promo>
                <![CDATA[true]]>
            </is_promo>
            <name>
                <![CDATA[Commander]]>
            </name>
        </set>
        <set>
            <date>
                <![CDATA[11/2013]]>
            </date>
            <code>
                <![CDATA[C13]]>
            </code>
            <is_promo>
                <![CDATA[true]]>
            </is_promo>
            <name>
                <![CDATA[Commander 2013 Edition]]>
            </name>
        </set>
        <set>
            <date>
                <![CDATA[11/2014]]>
            </date>
            <code>
                <![CDATA[C14]]>
            </code>
            <is_promo>
                <![CDATA[true]]>
            </is_promo>
            <name>
                <![CDATA[Commander 2014 Edition]]>
            </name>
        </set>
        <set>
            <date>
                <![CDATA[11/2015]]>
            </date>
            <code>
                <![CDATA[C15]]>
            </code>
            <is_promo>
                <![CDATA[true]]>
            </is_promo>
            <name>
                <![CDATA[Commander 2015 Edition]]>
            </name>
        </set>
        <set>
            <date>
                <![CDATA[11/2016]]>
            </date>
            <code>
                <![CDATA[C16]]>
            </code>
            <is_promo>
                <![CDATA[true]]>
            </is_promo>
            <name>
                <![CDATA[Commander 2016 Edition]]>
            </name>
        </set>
        <set>
            <date>
                <![CDATA[08/2017]]>
            </date>
            <code>
                <![CDATA[C17]]>
            </code>
            <is_promo>
                <![CDATA[true]]>
            </is_promo>
            <name>
                <![CDATA[Commander 2017 Edition]]>
            </name>
        </set>
        <set>
            <date>
                <![CDATA[08/2018]]>
            </date>
            <code>
                <![CDATA[C18]]>
            </code>
            <is_promo>
                <![CDATA[true]]>
            </is_promo>
            <name>
                <![CDATA[Commander 2018 Edition]]>
            </name>
        </set>
        <set>
            <date>
                <![CDATA[05/2017]]>
            </date>
            <code>
                <![CDATA[CMA]]>
            </code>
            <is_promo>
                <![CDATA[true]]>
            </is_promo>
            <name>
                <![CDATA[Commander Anthology]]>
            </name>
        </set>
        <set>
            <date>
                <![CDATA[06/2018]]>
            </date>
            <code>
                <![CDATA[CM2]]>
            </code>
            <is_promo>
                <![CDATA[true]]>
            </is_promo>
            <name>
                <![CDATA[Commander Anthology Volume II]]>
            </name>
        </set>
        <set>
            <date>
                <![CDATA[11/2012]]>
            </date>
            <code>
                <![CDATA[CM1]]>
            </code>
            <is_promo>
                <![CDATA[true]]>
            </is_promo>
            <name>
                <![CDATA[Commander's Arsenal]]>
            </name>
        </set>
        <set>
            <date>
                <![CDATA[01/2009]]>
            </date>
            <code>
                <![CDATA[CFX]]>
            </code>
            <is_promo>
                <![CDATA[false]]>
            </is_promo>
            <name>
                <![CDATA[Conflux]]>
            </name>
        </set>
        <set>
            <date>
                <![CDATA[06/2014]]>
            </date>
            <code>
                <![CDATA[CNS]]>
            </code>
            <is_promo>
                <![CDATA[true]]>
            </is_promo>
            <name>
                <![CDATA[Conspiracy]]>
            </name>
        </set>
        <set>
            <date>
                <![CDATA[06/2014]]>
            </date>
            <code>
                <![CDATA[CNSC]]>
            </code>
            <is_promo>
                <![CDATA[true]]>
            </is_promo>
            <name>
                <![CDATA[Conspiracy "Conspiracies"]]>
            </name>
        </set>
        <set>
            <date>
                <![CDATA[08/2016]]>
            </date>
            <code>
                <![CDATA[CN2]]>
            </code>
            <is_promo>
                <![CDATA[true]]>
            </is_promo>
            <name>
                <![CDATA[Conspiracy: Take the Crown]]>
            </name>
        </set>
        <set>
            <date>
                <![CDATA[08/2016]]>
            </date>
            <code>
                <![CDATA[CN2C]]>
            </code>
            <is_promo>
                <![CDATA[true]]>
            </is_promo>
            <name>
                <![CDATA[Conspiracy: Take the Crown "Conspiracies"]]>
            </name>
        </set>
        <set>
            <date>
                <![CDATA[02/2012]]>
            </date>
            <code>
                <![CDATA[DKA]]>
            </code>
            <is_promo>
                <![CDATA[false]]>
            </is_promo>
            <name>
                <![CDATA[Dark Ascension]]>
            </name>
        </set>
        <set>
            <date>
                <![CDATA[01/2004]]>
            </date>
            <code>
                <![CDATA[DST]]>
            </code>
            <is_promo>
                <![CDATA[false]]>
            </is_promo>
            <name>
                <![CDATA[Darksteel]]>
            </name>
        </set>
        <set>
            <date>
                <![CDATA[12/2001]]>
            </date>
            <code>
                <![CDATA[DKM]]>
            </code>
            <is_promo>
                <![CDATA[true]]>
            </is_promo>
            <name>
                <![CDATA[Deckmasters]]>
            </name>
        </set>
        <set>
            <date>
                <![CDATA[05/2014]]>
            </date>
            <code>
                <![CDATA[TDAG]]>
            </code>
            <is_promo>
                <![CDATA[true]]>
            </is_promo>
            <name>
                <![CDATA[Defeat a God]]>
            </name>
        </set>
        <set>
            <date>
                <![CDATA[04/2006]]>
            </date>
            <code>
                <![CDATA[DIS]]>
            </code>
            <is_promo>
                <![CDATA[false]]>
            </is_promo>
            <name>
                <![CDATA[Dissension]]>
            </name>
        </set>
        <set>
            <date>
                <![CDATA[04/2018]]>
            </date>
            <code>
                <![CDATA[DOM]]>
            </code>
            <is_promo>
                <![CDATA[false]]>
            </is_promo>
            <name>
                <![CDATA[Dominaria]]>
            </name>
        </set>
        <set>
            <date>
                <![CDATA[05/2013]]>
            </date>
            <code>
                <![CDATA[DGM]]>
            </code>
            <is_promo>
                <![CDATA[false]]>
            </is_promo>
            <name>
                <![CDATA[Dragon's Maze]]>
            </name>
        </set>
        <set>
            <date>
                <![CDATA[03/2015]]>
            </date>
            <code>
                <![CDATA[DTK]]>
            </code>
            <is_promo>
                <![CDATA[false]]>
            </is_promo>
            <name>
                <![CDATA[Dragons of Tarkir]]>
            </name>
        </set>
        <set>
            <date>
                <![CDATA[12/2014]]>
            </date>
            <code>
                <![CDATA[DD3D]]>
            </code>
            <is_promo>
                <![CDATA[true]]>
            </is_promo>
            <name>
                <![CDATA[Duel Decks Anthology, Divine vs. Demonic]]>
            </name>
        </set>
        <set>
            <date>
                <![CDATA[12/2014]]>
            </date>
            <code>
                <![CDATA[DD3E]]>
            </code>
            <is_promo>
                <![CDATA[true]]>
            </is_promo>
            <name>
                <![CDATA[Duel Decks Anthology, Elves vs. Goblins]]>
            </name>
        </set>
        <set>
            <date>
                <![CDATA[12/2014]]>
            </date>
            <code>
                <![CDATA[DD3G]]>
            </code>
            <is_promo>
                <![CDATA[true]]>
            </is_promo>
            <name>
                <![CDATA[Duel Decks Anthology, Garruk vs. Liliana]]>
            </name>
        </set>
        <set>
            <date>
                <![CDATA[12/2014]]>
            </date>
            <code>
                <![CDATA[DD3J]]>
            </code>
            <is_promo>
                <![CDATA[true]]>
            </is_promo>
            <name>
                <![CDATA[Duel Decks Anthology, Jace vs. Chandra]]>
            </name>
        </set>
        <set>
            <date>
                <![CDATA[08/2011]]>
            </date>
            <code>
                <![CDATA[DDH]]>
            </code>
            <is_promo>
                <![CDATA[true]]>
            </is_promo>
            <name>
                <![CDATA[Duel Decks: Ajani vs. Nicol Bolas]]>
            </name>
        </set>
        <set>
            <date>
                <![CDATA[02/2016]]>
            </date>
            <code>
                <![CDATA[DDQ]]>
            </code>
            <is_promo>
                <![CDATA[true]]>
            </is_promo>
            <name>
                <![CDATA[Duel Decks: Blessed vs. Cursed]]>
            </name>
        </set>
        <set>
            <date>
                <![CDATA[04/2009]]>
            </date>
            <code>
                <![CDATA[DDC]]>
            </code>
            <is_promo>
                <![CDATA[true]]>
            </is_promo>
            <name>
                <![CDATA[Duel Decks: Divine vs. Demonic]]>
            </name>
        </set>
        <set>
            <date>
                <![CDATA[02/2015]]>
            </date>
            <code>
                <![CDATA[DDO]]>
            </code>
            <is_promo>
                <![CDATA[true]]>
            </is_promo>
            <name>
                <![CDATA[Duel Decks: Elspeth vs. Kiora]]>
            </name>
        </set>
        <set>
            <date>
                <![CDATA[09/2010]]>
            </date>
            <code>
                <![CDATA[DDF]]>
            </code>
            <is_promo>
                <![CDATA[true]]>
            </is_promo>
            <name>
                <![CDATA[Duel Decks: Elspeth vs. Tezzeret]]>
            </name>
        </set>
        <set>
            <date>
                <![CDATA[11/2007]]>
            </date>
            <code>
                <![CDATA[EVG]]>
            </code>
            <is_promo>
                <![CDATA[true]]>
            </is_promo>
            <name>
                <![CDATA[Duel Decks: Elves vs. Goblins]]>
            </name>
        </set>
        <set>
            <date>
                <![CDATA[04/2018]]>
            </date>
            <code>
                <![CDATA[DDU]]>
            </code>
            <is_promo>
                <![CDATA[true]]>
            </is_promo>
            <name>
                <![CDATA[Duel Decks: Elves vs. Inventors]]>
            </name>
        </set>
        <set>
            <code>
                <![CDATA[DDD]]>
            </code>
            <name>
                <![CDATA[Duel Decks: Garruk vs. Liliana]]>
            </name>
            <date>
                <![CDATA[10/2009]]>
            </date>
            <is_promo>
                <![CDATA[true]]>
            </is_promo>
        </set>
        <set>
            <code>
                <![CDATA[DDL]]>
            </code>
            <name>
                <![CDATA[Duel Decks: Heroes vs. Monsters]]>
            </name>
            <date>
                <![CDATA[09/2013]]>
            </date>
            <is_promo>
                <![CDATA[true]]>
            </is_promo>
        </set>
        <set>
            <code>
                <![CDATA[DDJ]]>
            </code>
            <name>
                <![CDATA[Duel Decks: Izzet vs. Golgari]]>
            </name>
            <date>
                <![CDATA[09/2012]]>
            </date>
            <is_promo>
                <![CDATA[true]]>
            </is_promo>
        </set>
        <set>
            <code>
                <![CDATA[DD2]]>
            </code>
            <name>
                <![CDATA[Duel Decks: Jace vs. Chandra]]>
            </name>
            <date>
                <![CDATA[11/2008]]>
            </date>
            <is_promo>
                <![CDATA[true]]>
            </is_promo>
        </set>
        <set>
            <code>
                <![CDATA[DDM]]>
            </code>
            <name>
                <![CDATA[Duel Decks: Jace vs. Vraska]]>
            </name>
            <date>
                <![CDATA[03/2014]]>
            </date>
            <is_promo>
                <![CDATA[true]]>
            </is_promo>
        </set>
        <set>
            <code>
                <![CDATA[DDG]]>
            </code>
            <name>
                <![CDATA[Duel Decks: Knights vs. Dragons]]>
            </name>
            <date>
                <![CDATA[04/2011]]>
            </date>
            <is_promo>
                <![CDATA[true]]>
            </is_promo>
        </set>
        <set>
            <code>
                <![CDATA[DDT]]>
            </code>
            <name>
                <![CDATA[Duel Decks: Merfolk vs. Goblins]]>
            </name>
            <date>
                <![CDATA[11/2017]]>
            </date>
            <is_promo>
                <![CDATA[true]]>
            </is_promo>
        </set>
        <set>
            <code>
                <![CDATA[DDS]]>
            </code>
            <name>
                <![CDATA[Duel Decks: Mind vs. Might]]>
            </name>
            <date>
                <![CDATA[03/2017]]>
            </date>
            <is_promo>
                <![CDATA[true]]>
            </is_promo>
        </set>
        <set>
            <code>
                <![CDATA[DDR]]>
            </code>
            <name>
                <![CDATA[Duel Decks: Nissa vs. Ob Nixilis]]>
            </name>
            <date>
                <![CDATA[09/2016]]>
            </date>
            <is_promo>
                <![CDATA[true]]>
            </is_promo>
        </set>
        <set>
            <code>
                <![CDATA[DDE]]>
            </code>
            <name>
                <![CDATA[Duel Decks: Phyrexia vs. the Coalition]]>
            </name>
            <date>
                <![CDATA[03/2010]]>
            </date>
            <is_promo>
                <![CDATA[true]]>
            </is_promo>
        </set>
        <set>
            <code>
                <![CDATA[DDK]]>
            </code>
            <name>
                <![CDATA[Duel Decks: Sorin vs. Tibalt]]>
            </name>
            <date>
                <![CDATA[03/2013]]>
            </date>
            <is_promo>
                <![CDATA[true]]>
            </is_promo>
        </set>
        <set>
            <code>
                <![CDATA[DDN]]>
            </code>
            <name>
                <![CDATA[Duel Decks: Speed vs. Cunning]]>
            </name>
            <date>
                <![CDATA[09/2014]]>
            </date>
            <is_promo>
                <![CDATA[true]]>
            </is_promo>
        </set>
        <set>
            <code>
                <![CDATA[DDI]]>
            </code>
            <name>
                <![CDATA[Duel Decks: Venser vs. Koth]]>
            </name>
            <date>
                <![CDATA[04/2012]]>
            </date>
            <is_promo>
                <![CDATA[true]]>
            </is_promo>
        </set>
        <set>
            <code>
                <![CDATA[DDP]]>
            </code>
            <name>
                <![CDATA[Duel Decks: Zendikar vs. Eldrazi]]>
            </name>
            <date>
                <![CDATA[08/2015]]>
            </date>
            <is_promo>
                <![CDATA[true]]>
            </is_promo>
        </set>
        <set>
            <code>
                <![CDATA[DPW]]>
            </code>
            <name>
                <![CDATA[Duels of the Planeswalkers]]>
            </name>
            <date>
                <![CDATA[04/2010]]>
            </date>
            <is_promo>
                <![CDATA[true]]>
            </is_promo>
        </set>
        <set>
            <code>
                <![CDATA[8ED]]>
            </code>
            <name>
                <![CDATA[Eighth Edition]]>
            </name>
            <date>
                <![CDATA[07/2003]]>
            </date>
            <is_promo>
                <![CDATA[false]]>
            </is_promo>
        </set>
        <set>
            <code>
                <![CDATA[EMN]]>
            </code>
            <name>
                <![CDATA[Eldritch Moon]]>
            </name>
            <date>
                <![CDATA[07/2016]]>
            </date>
            <is_promo>
                <![CDATA[false]]>
            </is_promo>
        </set>
        <set>
            <code>
                <![CDATA[EMA]]>
            </code>
            <name>
                <![CDATA[Eternal Masters]]>
            </name>
            <date>
                <![CDATA[06/2016]]>
            </date>
            <is_promo>
                <![CDATA[true]]>
            </is_promo>
        </set>
        <set>
            <code>
                <![CDATA[EURO]]>
            </code>
            <name>
                <![CDATA[European Land Program]]>
            </name>
            <date>
                <![CDATA[00/0000]]>
            </date>
            <is_promo>
                <![CDATA[true]]>
            </is_promo>
        </set>
        <set>
            <code>
                <![CDATA[EVE]]>
            </code>
            <name>
                <![CDATA[Eventide]]>
            </name>
            <date>
                <![CDATA[07/2008]]>
            </date>
            <is_promo>
                <![CDATA[false]]>
            </is_promo>
        </set>
        <set>
            <code>
                <![CDATA[EXO]]>
            </code>
            <name>
                <![CDATA[Exodus]]>
            </name>
            <date>
                <![CDATA[06/1998]]>
            </date>
            <is_promo>
                <![CDATA[false]]>
            </is_promo>
        </set>
        <set>
            <code>
                <![CDATA[E02]]>
            </code>
            <name>
                <![CDATA[Explorers of Ixalan]]>
            </name>
            <date>
                <![CDATA[11/2017]]>
            </date>
            <is_promo>
                <![CDATA[true]]>
            </is_promo>
        </set>
        <set>
            <code>
                <![CDATA[TFTH]]>
            </code>
            <name>
                <![CDATA[Face the Hydra]]>
            </name>
            <date>
                <![CDATA[09/2013]]>
            </date>
            <is_promo>
                <![CDATA[true]]>
            </is_promo>
        </set>
        <set>
            <code>
                <![CDATA[FEM]]>
            </code>
            <name>
                <![CDATA[Fallen Empires]]>
            </name>
            <date>
                <![CDATA[10/1994]]>
            </date>
            <is_promo>
                <![CDATA[false]]>
            </is_promo>
        </set>
        <set>
            <code>
                <![CDATA[FRF]]>
            </code>
            <name>
                <![CDATA[Fate Reforged]]>
            </name>
            <date>
                <![CDATA[01/2015]]>
            </date>
            <is_promo>
                <![CDATA[false]]>
            </is_promo>
        </set>
        <set>
            <code>
                <![CDATA[5DN]]>
            </code>
            <name>
                <![CDATA[Fifth Dawn]]>
            </name>
            <date>
                <![CDATA[05/2004]]>
            </date>
            <is_promo>
                <![CDATA[false]]>
            </is_promo>
        </set>
        <set>
            <code>
                <![CDATA[5ED]]>
            </code>
            <name>
                <![CDATA[Fifth Edition]]>
            </name>
            <date>
                <![CDATA[03/1997]]>
            </date>
            <is_promo>
                <![CDATA[false]]>
            </is_promo>
        </set>
        <set>
            <code>
                <![CDATA[4ED]]>
            </code>
            <name>
                <![CDATA[Fourth Edition]]>
            </name>
            <date>
                <![CDATA[04/1995]]>
            </date>
            <is_promo>
                <![CDATA[false]]>
            </is_promo>
        </set>
        <set>
            <code>
                <![CDATA[FNM]]>
            </code>
            <name>
                <![CDATA[Friday Night Magic]]>
            </name>
            <date>
                <![CDATA[00/0000]]>
            </date>
            <is_promo>
                <![CDATA[true]]>
            </is_promo>
        </set>
        <set>
            <code>
                <![CDATA[V15]]>
            </code>
            <name>
                <![CDATA[From the Vault: Angels]]>
            </name>
            <date>
                <![CDATA[08/2015]]>
            </date>
            <is_promo>
                <![CDATA[true]]>
            </is_promo>
        </set>
        <set>
            <code>
                <![CDATA[V14]]>
            </code>
            <name>
                <![CDATA[From the Vault: Annihilation]]>
            </name>
            <date>
                <![CDATA[08/2014]]>
            </date>
            <is_promo>
                <![CDATA[true]]>
            </is_promo>
        </set>
        <set>
            <code>
                <![CDATA[DRB]]>
            </code>
            <name>
                <![CDATA[From the Vault: Dragons]]>
            </name>
            <date>
                <![CDATA[08/2008]]>
            </date>
            <is_promo>
                <![CDATA[true]]>
            </is_promo>
        </set>
        <set>
            <code>
                <![CDATA[V09]]>
            </code>
            <name>
                <![CDATA[From the Vault: Exiled]]>
            </name>
            <date>
                <![CDATA[08/2009]]>
            </date>
            <is_promo>
                <![CDATA[true]]>
            </is_promo>
        </set>
        <set>
            <code>
                <![CDATA[V11]]>
            </code>
            <name>
                <![CDATA[From the Vault: Legends]]>
            </name>
            <date>
                <![CDATA[08/2011]]>
            </date>
            <is_promo>
                <![CDATA[true]]>
            </is_promo>
        </set>
        <set>
            <code>
                <![CDATA[V16]]>
            </code>
            <name>
                <![CDATA[From the Vault: Lore]]>
            </name>
            <date>
                <![CDATA[08/2016]]>
            </date>
            <is_promo>
                <![CDATA[true]]>
            </is_promo>
        </set>
        <set>
            <code>
                <![CDATA[V12]]>
            </code>
            <name>
                <![CDATA[From the Vault: Realms]]>
            </name>
            <date>
                <![CDATA[08/2012]]>
            </date>
            <is_promo>
                <![CDATA[true]]>
            </is_promo>
        </set>
        <set>
            <code>
                <![CDATA[V10]]>
            </code>
            <name>
                <![CDATA[From the Vault: Relics]]>
            </name>
            <date>
                <![CDATA[08/2010]]>
            </date>
            <is_promo>
                <![CDATA[true]]>
            </is_promo>
        </set>
        <set>
            <code>
                <![CDATA[V17]]>
            </code>
            <name>
                <![CDATA[From the Vault: Transform]]>
            </name>
            <date>
                <![CDATA[11/2017]]>
            </date>
            <is_promo>
                <![CDATA[true]]>
            </is_promo>
        </set>
        <set>
            <code>
                <![CDATA[V13]]>
            </code>
            <name>
                <![CDATA[From the Vault: Twenty]]>
            </name>
            <date>
                <![CDATA[08/2013]]>
            </date>
            <is_promo>
                <![CDATA[true]]>
            </is_promo>
        </set>
        <set>
            <code>
                <![CDATA[FUT]]>
            </code>
            <name>
                <![CDATA[Future Sight]]>
            </name>
            <date>
                <![CDATA[05/2007]]>
            </date>
            <is_promo>
                <![CDATA[false]]>
            </is_promo>
        </set>
        <set>
            <code>
                <![CDATA[GNT]]>
            </code>
            <name>
                <![CDATA[Game Night]]>
            </name>
            <date>
                <![CDATA[11/2018]]>
            </date>
            <is_promo>
                <![CDATA[true]]>
            </is_promo>
        </set>
        <set>
            <code>
                <![CDATA[GTC]]>
            </code>
            <name>
                <![CDATA[Gatecrash]]>
            </name>
            <date>
                <![CDATA[01/2013]]>
            </date>
            <is_promo>
                <![CDATA[false]]>
            </is_promo>
        </set>
        <set>
            <code>
                <![CDATA[GTW]]>
            </code>
            <name>
                <![CDATA[Gateway]]>
            </name>
            <date>
                <![CDATA[00/0000]]>
            </date>
            <is_promo>
                <![CDATA[true]]>
            </is_promo>
        </set>
        <set>
            <code>
                <![CDATA[GS1]]>
            </code>
            <name>
                <![CDATA[Global Series: Jiang Yanggu and Mu Yanling]]>
            </name>
            <date>
                <![CDATA[06/2018]]>
            </date>
            <is_promo>
                <![CDATA[true]]>
            </is_promo>
        </set>
        <set>
            <code>
                <![CDATA[GPX]]>
            </code>
            <name>
                <![CDATA[Grand Prix]]>
            </name>
            <date>
                <![CDATA[00/0000]]>
            </date>
            <is_promo>
                <![CDATA[true]]>
            </is_promo>
        </set>
        <set>
            <code>
                <![CDATA[GPT]]>
            </code>
            <name>
                <![CDATA[Guildpact]]>
            </name>
            <date>
                <![CDATA[01/2006]]>
            </date>
            <is_promo>
                <![CDATA[false]]>
            </is_promo>
        </set>
        <set>
            <code>
                <![CDATA[GRN]]>
            </code>
            <name>
                <![CDATA[Guilds of Ravnica]]>
            </name>
            <date>
                <![CDATA[10/2018]]>
            </date>
            <is_promo>
                <![CDATA[false]]>
            </is_promo>
        </set>
        <set>
            <code>
                <![CDATA[GK1]]>
            </code>
            <name>
                <![CDATA[Guilds of Ravnica Guild Kit]]>
            </name>
            <date>
                <![CDATA[10/2018]]>
            </date>
            <is_promo>
                <![CDATA[true]]>
            </is_promo>
        </set>
        <set>
            <code>
                <![CDATA[MED]]>
            </code>
            <name>
                <![CDATA[Guilds of Ravnica Mythic Edition]]>
            </name>
            <date>
                <![CDATA[10/2018]]>
            </date>
            <is_promo>
                <![CDATA[true]]>
            </is_promo>
        </set>
        <set>
            <code>
                <![CDATA[MED]]>
            </code>
            <name>
                <![CDATA[Guilds of Ravnica Mythic Edition]]>
            </name>
            <date>
                <![CDATA[10/2018]]>
            </date>
            <is_promo>
                <![CDATA[true]]>
            </is_promo>
        </set>
        <set>
            <code>
                <![CDATA[GUR]]>
            </code>
            <name>
                <![CDATA[Guru]]>
            </name>
            <date>
                <![CDATA[00/0000]]>
            </date>
            <is_promo>
                <![CDATA[true]]>
            </is_promo>
        </set>
        <set>
            <code>
                <![CDATA[PHUK]]>
            </code>
            <name>
                <![CDATA[Hachette UK]]>
            </name>
            <date>
                <![CDATA[02/2006]]>
            </date>
            <is_promo>
                <![CDATA[true]]>
            </is_promo>
        </set>
        <set>
            <code>
                <![CDATA[HHO]]>
            </code>
            <name>
                <![CDATA[Happy Holidays]]>
            </name>
            <date>
                <![CDATA[00/0000]]>
            </date>
            <is_promo>
                <![CDATA[true]]>
            </is_promo>
        </set>
        <set>
            <code>
                <![CDATA[HTR]]>
            </code>
            <name>
                <![CDATA[Heroes of the Realm]]>
            </name>
            <date>
                <![CDATA[00/0000]]>
            </date>
            <is_promo>
                <![CDATA[true]]>
            </is_promo>
        </set>
        <set>
            <code>
                <![CDATA[THP]]>
            </code>
            <name>
                <![CDATA[Hero's Path]]>
            </name>
            <date>
                <![CDATA[09/2013]]>
            </date>
            <is_promo>
                <![CDATA[true]]>
            </is_promo>
        </set>
        <set>
            <code>
                <![CDATA[HLM]]>
            </code>
            <name>
                <![CDATA[Homelands]]>
            </name>
            <date>
                <![CDATA[10/1995]]>
            </date>
            <is_promo>
                <![CDATA[false]]>
            </is_promo>
        </set>
        <set>
            <code>
                <![CDATA[HOU]]>
            </code>
            <name>
                <![CDATA[Hour of Devastation]]>
            </name>
            <date>
                <![CDATA[07/2017]]>
            </date>
            <is_promo>
                <![CDATA[false]]>
            </is_promo>
        </set>
        <set>
            <code>
                <![CDATA[ICE]]>
            </code>
            <name>
                <![CDATA[Ice Age]]>
            </name>
            <date>
                <![CDATA[06/1995]]>
            </date>
            <is_promo>
                <![CDATA[false]]>
            </is_promo>
        </set>
        <set>
            <code>
                <![CDATA[IMA]]>
            </code>
            <name>
                <![CDATA[Iconic Masters]]>
            </name>
            <date>
                <![CDATA[11/2017]]>
            </date>
            <is_promo>
                <![CDATA[true]]>
            </is_promo>
        </set>
        <set>
            <code>
                <![CDATA[ISD]]>
            </code>
            <name>
                <![CDATA[Innistrad]]>
            </name>
            <date>
                <![CDATA[09/2011]]>
            </date>
            <is_promo>
                <![CDATA[false]]>
            </is_promo>
        </set>
        <set>
            <code>
                <![CDATA[INV]]>
            </code>
            <name>
                <![CDATA[Invasion]]>
            </name>
            <date>
                <![CDATA[09/2000]]>
            </date>
            <is_promo>
                <![CDATA[false]]>
            </is_promo>
        </set>
        <set>
            <code>
                <![CDATA[XLN]]>
            </code>
            <name>
                <![CDATA[Ixalan]]>
            </name>
            <date>
                <![CDATA[09/2017]]>
            </date>
            <is_promo>
                <![CDATA[false]]>
            </is_promo>
        </set>
        <set>
            <code>
                <![CDATA[PXTC]]>
            </code>
            <name>
                <![CDATA[Ixalan Treasure Chest]]>
            </name>
            <date>
                <![CDATA[11/2017]]>
            </date>
            <is_promo>
                <![CDATA[true]]>
            </is_promo>
        </set>
        <set>
            <code>
                <![CDATA[JOU]]>
            </code>
            <name>
                <![CDATA[Journey into Nyx]]>
            </name>
            <date>
                <![CDATA[05/2014]]>
            </date>
            <is_promo>
                <![CDATA[false]]>
            </is_promo>
        </set>
        <set>
            <name>
                <![CDATA[Judge Gift Program]]>
            </name>
            <date>
                <![CDATA[00/0000]]>
            </date>
            <code>
                <![CDATA[JGP]]>
            </code>
            <is_promo>
                <![CDATA[true]]>
            </is_promo>
        </set>
        <set>
            <name>
                <![CDATA[Judgment]]>
            </name>
            <date>
                <![CDATA[05/2002]]>
            </date>
            <code>
                <![CDATA[JUD]]>
            </code>
            <is_promo>
                <![CDATA[false]]>
            </is_promo>
        </set>
        <set>
            <name>
                <![CDATA[Kaladesh]]>
            </name>
            <date>
                <![CDATA[09/2016]]>
            </date>
            <code>
                <![CDATA[KLD]]>
            </code>
            <is_promo>
                <![CDATA[false]]>
            </is_promo>
        </set>
        <set>
            <name>
                <![CDATA[Khans of Tarkir]]>
            </name>
            <date>
                <![CDATA[09/2014]]>
            </date>
            <code>
                <![CDATA[KTK]]>
            </code>
            <is_promo>
                <![CDATA[false]]>
            </is_promo>
        </set>
        <set>
            <name>
                <![CDATA[Legacy Championship]]>
            </name>
            <date>
                <![CDATA[00/0000]]>
            </date>
            <code>
                <![CDATA[OLGC]]>
            </code>
            <is_promo>
                <![CDATA[true]]>
            </is_promo>
        </set>
        <set>
            <name>
                <![CDATA[Legendary Cube]]>
            </name>
            <date>
                <![CDATA[11/2015]]>
            </date>
            <code>
                <![CDATA[PZ1]]>
            </code>
            <is_promo>
                <![CDATA[true]]>
            </is_promo>
        </set>
        <set>
            <name>
                <![CDATA[Legends]]>
            </name>
            <date>
                <![CDATA[06/1994]]>
            </date>
            <code>
                <![CDATA[LEG]]>
            </code>
            <is_promo>
                <![CDATA[false]]>
            </is_promo>
        </set>
        <set>
            <name>
                <![CDATA[Legions]]>
            </name>
            <date>
                <![CDATA[01/2003]]>
            </date>
            <code>
                <![CDATA[LGN]]>
            </code>
            <is_promo>
                <![CDATA[false]]>
            </is_promo>
        </set>
        <set>
            <name>
                <![CDATA[Limited Edition Alpha]]>
            </name>
            <date>
                <![CDATA[08/1993]]>
            </date>
            <code>
                <![CDATA[LEA]]>
            </code>
            <is_promo>
                <![CDATA[false]]>
            </is_promo>
        </set>
        <set>
            <name>
                <![CDATA[Limited Edition Beta]]>
            </name>
            <date>
                <![CDATA[10/1993]]>
            </date>
            <code>
                <![CDATA[LEB]]>
            </code>
            <is_promo>
                <![CDATA[false]]>
            </is_promo>
        </set>
        <set>
            <name>
                <![CDATA[Lorwyn]]>
            </name>
            <date>
                <![CDATA[09/2007]]>
            </date>
            <code>
                <![CDATA[LRW]]>
            </code>
            <is_promo>
                <![CDATA[false]]>
            </is_promo>
        </set>
        <set>
            <name>
                <![CDATA[Magic 2010 Core Set]]>
            </name>
            <date>
                <![CDATA[07/2009]]>
            </date>
            <code>
                <![CDATA[M10]]>
            </code>
            <is_promo>
                <![CDATA[false]]>
            </is_promo>
        </set>
        <set>
            <name>
                <![CDATA[Magic 2011 Core Set]]>
            </name>
            <date>
                <![CDATA[07/2010]]>
            </date>
            <code>
                <![CDATA[M11]]>
            </code>
            <is_promo>
                <![CDATA[false]]>
            </is_promo>
        </set>
        <set>
            <name>
                <![CDATA[Magic 2012 Core Set]]>
            </name>
            <date>
                <![CDATA[07/2011]]>
            </date>
            <code>
                <![CDATA[M12]]>
            </code>
            <is_promo>
                <![CDATA[false]]>
            </is_promo>
        </set>
        <set>
            <name>
                <![CDATA[Magic 2013 Core Set]]>
            </name>
            <date>
                <![CDATA[07/2012]]>
            </date>
            <code>
                <![CDATA[M13]]>
            </code>
            <is_promo>
                <![CDATA[false]]>
            </is_promo>
        </set>
        <set>
            <name>
                <![CDATA[Magic 2014 Core Set]]>
            </name>
            <date>
                <![CDATA[07/2013]]>
            </date>
            <code>
                <![CDATA[M14]]>
            </code>
            <is_promo>
                <![CDATA[false]]>
            </is_promo>
        </set>
        <set>
            <name>
                <![CDATA[Magic 2015 Core Set]]>
            </name>
            <date>
                <![CDATA[07/2014]]>
            </date>
            <code>
                <![CDATA[M15]]>
            </code>
            <is_promo>
                <![CDATA[false]]>
            </is_promo>
        </set>
        <set>
            <name>
                <![CDATA[Magic 2019 Core Set]]>
            </name>
            <date>
                <![CDATA[07/2018]]>
            </date>
            <code>
                <![CDATA[M19]]>
            </code>
            <is_promo>
                <![CDATA[false]]>
            </is_promo>
        </set>
        <set>
            <name>
                <![CDATA[Magic Online Promos]]>
            </name>
            <date>
                <![CDATA[00/0000]]>
            </date>
            <code>
                <![CDATA[PRM]]>
            </code>
            <is_promo>
                <![CDATA[true]]>
            </is_promo>
        </set>
        <set>
            <name>
                <![CDATA[Magic Origins]]>
            </name>
            <date>
                <![CDATA[07/2015]]>
            </date>
            <code>
                <![CDATA[ORI]]>
            </code>
            <is_promo>
                <![CDATA[false]]>
            </is_promo>
        </set>
        <set>
            <name>
                <![CDATA[Magic Player Rewards]]>
            </name>
            <date>
                <![CDATA[00/0000]]>
            </date>
            <code>
                <![CDATA[MPRP]]>
            </code>
            <is_promo>
                <![CDATA[true]]>
            </is_promo>
        </set>
        <set>
            <name>
                <![CDATA[Magic Premiere Shop]]>
            </name>
            <date>
                <![CDATA[00/0000]]>
            </date>
            <code>
                <![CDATA[MPS]]>
            </code>
            <is_promo>
                <![CDATA[true]]>
            </is_promo>
        </set>
        <set>
            <name>
                <![CDATA[Masterpiece Series: Amonkhet Invocations]]>
            </name>
            <date>
                <![CDATA[04/2017]]>
            </date>
            <code>
                <![CDATA[MPSAKH]]>
            </code>
            <is_promo>
                <![CDATA[true]]>
            </is_promo>
        </set>
        <set>
            <name>
                <![CDATA[Masterpiece Series: Kaladesh Inventions]]>
            </name>
            <date>
                <![CDATA[09/2016]]>
            </date>
            <code>
                <![CDATA[MPSKLD]]>
            </code>
            <is_promo>
                <![CDATA[true]]>
            </is_promo>
        </set>
        <set>
            <name>
                <![CDATA[Masterpiece Series: Zendikar Expeditions]]>
            </name>
            <date>
                <![CDATA[10/2015]]>
            </date>
            <code>
                <![CDATA[MPSZEN]]>
            </code>
            <is_promo>
                <![CDATA[true]]>
            </is_promo>
        </set>
        <set>
            <name>
                <![CDATA[Masters 25]]>
            </name>
            <date>
                <![CDATA[03/2018]]>
            </date>
            <code>
                <![CDATA[A25]]>
            </code>
            <is_promo>
                <![CDATA[true]]>
            </is_promo>
        </set>
        <set>
            <name>
                <![CDATA[Masters Edition]]>
            </name>
            <date>
                <![CDATA[09/2007]]>
            </date>
            <code>
                <![CDATA[ME1]]>
            </code>
            <is_promo>
                <![CDATA[true]]>
            </is_promo>
        </set>
        <set>
            <name>
                <![CDATA[Masters Edition II]]>
            </name>
            <date>
                <![CDATA[09/2008]]>
            </date>
            <code>
                <![CDATA[ME2]]>
            </code>
            <is_promo>
                <![CDATA[true]]>
            </is_promo>
        </set>
        <set>
            <name>
                <![CDATA[Masters Edition III]]>
            </name>
            <date>
                <![CDATA[09/2009]]>
            </date>
            <code>
                <![CDATA[ME3]]>
            </code>
            <is_promo>
                <![CDATA[true]]>
            </is_promo>
        </set>
        <set>
            <name>
                <![CDATA[Masters Edition IV]]>
            </name>
            <date>
                <![CDATA[01/2011]]>
            </date>
            <code>
                <![CDATA[ME4]]>
            </code>
            <is_promo>
                <![CDATA[true]]>
            </is_promo>
        </set>
        <set>
            <name>
                <![CDATA[Media Inserts]]>
            </name>
            <date>
                <![CDATA[00/000]]>
            </date>
            <code>
                <![CDATA[MDI]]>
            </code>
            <is_promo>
                <![CDATA[true]]>
            </is_promo>
        </set>
        <set>
            <name>
                <![CDATA[Mercadian Masques]]>
            </name>
            <date>
                <![CDATA[09/1999]]>
            </date>
            <code>
                <![CDATA[MMQ]]>
            </code>
            <is_promo>
                <![CDATA[false]]>
            </is_promo>
        </set>
        <set>
            <name>
                <![CDATA[Mirage]]>
            </name>
            <date>
                <![CDATA[10/1996]]>
            </date>
            <code>
                <![CDATA[MIR]]>
            </code>
            <is_promo>
                <![CDATA[false]]>
            </is_promo>
        </set>
        <set>
            <name>
                <![CDATA[Mirrodin]]>
            </name>
            <date>
                <![CDATA[09/2003]]>
            </date>
            <code>
                <![CDATA[MRD]]>
            </code>
            <is_promo>
                <![CDATA[false]]>
            </is_promo>
        </set>
        <set>
            <name>
                <![CDATA[Mirrodin Besieged]]>
            </name>
            <date>
                <![CDATA[01/2011]]>
            </date>
            <code>
                <![CDATA[MBS]]>
            </code>
            <is_promo>
                <![CDATA[false]]>
            </is_promo>
        </set>
        <set>
            <name>
                <![CDATA[Modern Event Deck 2014]]>
            </name>
            <date>
                <![CDATA[05/2014]]>
            </date>
            <code>
                <![CDATA[MD1]]>
            </code>
            <is_promo>
                <![CDATA[true]]>
            </is_promo>
        </set>
        <set>
            <name>
                <![CDATA[Modern Masters]]>
            </name>
            <date>
                <![CDATA[06/2013]]>
            </date>
            <code>
                <![CDATA[MMA]]>
            </code>
            <is_promo>
                <![CDATA[true]]>
            </is_promo>
        </set>
        <set>
            <name>
                <![CDATA[Modern Masters 2015 Edition]]>
            </name>
            <date>
                <![CDATA[05/2015]]>
            </date>
            <code>
                <![CDATA[MM2]]>
            </code>
            <is_promo>
                <![CDATA[true]]>
            </is_promo>
        </set>
        <set>
            <name>
                <![CDATA[Modern Masters 2017 Edition]]>
            </name>
            <date>
                <![CDATA[03/2017]]>
            </date>
            <code>
                <![CDATA[MM3]]>
            </code>
            <is_promo>
                <![CDATA[true]]>
            </is_promo>
        </set>
        <set>
            <name>
                <![CDATA[Morningtide]]>
            </name>
            <date>
                <![CDATA[01/2008]]>
            </date>
            <code>
                <![CDATA[MOR]]>
            </code>
            <is_promo>
                <![CDATA[false]]>
            </is_promo>
        </set>
        <set>
            <name>
                <![CDATA[Nemesis]]>
            </name>
            <date>
                <![CDATA[02/2000]]>
            </date>
            <code>
                <![CDATA[NMS]]>
            </code>
            <is_promo>
                <![CDATA[false]]>
            </is_promo>
        </set>
        <set>
            <name>
                <![CDATA[New Phyrexia]]>
            </name>
            <date>
                <![CDATA[05/2011]]>
            </date>
            <code>
                <![CDATA[NPH]]>
            </code>
            <is_promo>
                <![CDATA[false]]>
            </is_promo>
        </set>
        <set>
            <name>
                <![CDATA[Ninth Edition]]>
            </name>
            <date>
                <![CDATA[07/2005]]>
            </date>
            <code>
                <![CDATA[9ED]]>
            </code>
            <is_promo>
                <![CDATA[false]]>
            </is_promo>
        </set>
        <set>
            <name>
                <![CDATA[Oath of the Gatewatch]]>
            </name>
            <date>
                <![CDATA[01/2016]]>
            </date>
            <code>
                <![CDATA[OGW]]>
            </code>
            <is_promo>
                <![CDATA[false]]>
            </is_promo>
        </set>
        <set>
            <name>
                <![CDATA[Odyssey]]>
            </name>
            <date>
                <![CDATA[09/2001]]>
            </date>
            <code>
                <![CDATA[ODY]]>
            </code>
            <is_promo>
                <![CDATA[false]]>
            </is_promo>
        </set>
        <set>
            <name>
                <![CDATA[Onslaught]]>
            </name>
            <date>
                <![CDATA[09/2002]]>
            </date>
            <code>
                <![CDATA[ONS]]>
            </code>
            <is_promo>
                <![CDATA[false]]>
            </is_promo>
        </set>
        <set>
            <name>
                <![CDATA[Planar Chaos]]>
            </name>
            <date>
                <![CDATA[01/2007]]>
            </date>
            <code>
                <![CDATA[PLC]]>
            </code>
            <is_promo>
                <![CDATA[false]]>
            </is_promo>
        </set>
        <set>
            <name>
                <![CDATA[Planechase]]>
            </name>
            <date>
                <![CDATA[09/2009]]>
            </date>
            <code>
                <![CDATA[HOP]]>
            </code>
            <is_promo>
                <![CDATA[true]]>
            </is_promo>
        </set>
        <set>
            <name>
                <![CDATA[Planechase "Planes"]]>
            </name>
            <date>
                <![CDATA[09/2009]]>
            </date>
            <code>
                <![CDATA[HOPP]]>
            </code>
            <is_promo>
                <![CDATA[true]]>
            </is_promo>
        </set>
        <set>
            <name>
                <![CDATA[Planechase 2012 Edition]]>
            </name>
            <date>
                <![CDATA[06/2012]]>
            </date>
            <code>
                <![CDATA[PC2]]>
            </code>
            <is_promo>
                <![CDATA[true]]>
            </is_promo>
        </set>
        <set>
            <name>
                <![CDATA[Planechase 2012 Edition "Planes" and "Phenomena"]]>
            </name>
            <date>
                <![CDATA[06/2012]]>
            </date>
            <code>
                <![CDATA[PC2P]]>
            </code>
            <is_promo>
                <![CDATA[true]]>
            </is_promo>
        </set>
        <set>
            <name>
                <![CDATA[Planechase Anthology]]>
            </name>
            <date>
                <![CDATA[11/2016]]>
            </date>
            <code>
                <![CDATA[PCA]]>
            </code>
            <is_promo>
                <![CDATA[true]]>
            </is_promo>
        </set>
        <set>
            <name>
                <![CDATA[Planechase Anthology "Planes" and "Phenomena"]]>
            </name>
            <date>
                <![CDATA[11/2016]]>
            </date>
            <code>
                <![CDATA[PCAP]]>
            </code>
            <is_promo>
                <![CDATA[true]]>
            </is_promo>
        </set>
        <set>
            <name>
                <![CDATA[Planeshift]]>
            </name>
            <date>
                <![CDATA[01/2001]]>
            </date>
            <code>
                <![CDATA[PLS]]>
            </code>
            <is_promo>
                <![CDATA[false]]>
            </is_promo>
        </set>
        <set>
            <name>
                <![CDATA[Portal]]>
            </name>
            <date>
                <![CDATA[06/1997]]>
            </date>
            <code>
                <![CDATA[POR]]>
            </code>
            <is_promo>
                <![CDATA[true]]>
            </is_promo>
        </set>
        <set>
            <name>
                <![CDATA[Portal Second Age]]>
            </name>
            <date>
                <![CDATA[06/1998]]>
            </date>
            <code>
                <![CDATA[PO2]]>
            </code>
            <is_promo>
                <![CDATA[true]]>
            </is_promo>
        </set>
        <set>
            <name>
                <![CDATA[Portal Three Kingdoms]]>
            </name>
            <date>
                <![CDATA[06/1999]]>
            </date>
            <code>
                <![CDATA[PTK]]>
            </code>
            <is_promo>
                <![CDATA[true]]>
            </is_promo>
        </set>
        <set>
            <name>
                <![CDATA[Premium Deck Series: Fire and Lightning]]>
            </name>
            <date>
                <![CDATA[11/2010]]>
            </date>
            <code>
                <![CDATA[PD2]]>
            </code>
            <is_promo>
                <![CDATA[true]]>
            </is_promo>
        </set>
        <set>
            <name>
                <![CDATA[Premium Deck Series: Graveborn]]>
            </name>
            <date>
                <![CDATA[11/2011]]>
            </date>
            <code>
                <![CDATA[PD3]]>
            </code>
            <is_promo>
                <![CDATA[true]]>
            </is_promo>
        </set>
        <set>
            <name>
                <![CDATA[Premium Deck Series: Slivers]]>
            </name>
            <date>
                <![CDATA[11/2009]]>
            </date>
            <code>
                <![CDATA[H09]]>
            </code>
            <is_promo>
                <![CDATA[true]]>
            </is_promo>
        </set>
        <set>
            <name>
                <![CDATA[Pro Tour Promos]]>
            </name>
            <date>
                <![CDATA[00/0000]]>
            </date>
            <code>
                <![CDATA[PRO]]>
            </code>
            <is_promo>
                <![CDATA[true]]>
            </is_promo>
        </set>
        <set>
            <name>
                <![CDATA[Prophecy]]>
            </name>
            <date>
                <![CDATA[05/2000]]>
            </date>
            <code>
                <![CDATA[PCY]]>
            </code>
            <is_promo>
                <![CDATA[false]]>
            </is_promo>
        </set>
        <set>
            <name>
                <![CDATA[Ravnica: City of Guilds]]>
            </name>
            <date>
                <![CDATA[09/2005]]>
            </date>
            <code>
                <![CDATA[RAV]]>
            </code>
            <is_promo>
                <![CDATA[false]]>
            </is_promo>
        </set>
        <set>
            <name>
                <![CDATA[Release Promos]]>
            </name>
            <date>
                <![CDATA[00/0000]]>
            </date>
            <code>
                <![CDATA[RLS]]>
            </code>
            <is_promo>
                <![CDATA[true]]>
            </is_promo>
        </set>
        <set>
            <name>
                <![CDATA[Renaissance]]>
            </name>
            <date>
                <![CDATA[08/1995]]>
            </date>
            <code>
                <![CDATA[REN]]>
            </code>
            <is_promo>
                <![CDATA[false]]>
            </is_promo>
        </set>
        <set>
            <name>
                <![CDATA[Return to Ravnica]]>
            </name>
            <date>
                <![CDATA[10/2012]]>
            </date>
            <code>
                <![CDATA[RTR]]>
            </code>
            <is_promo>
                <![CDATA[false]]>
            </is_promo>
        </set>
        <set>
            <name>
                <![CDATA[Revised Edition]]>
            </name>
            <date>
                <![CDATA[04/1994]]>
            </date>
            <code>
                <![CDATA[3ED]]>
            </code>
            <is_promo>
                <![CDATA[false]]>
            </is_promo>
        </set>
        <set>
            <name>
                <![CDATA[Rise of the Eldrazi]]>
            </name>
            <date>
                <![CDATA[04/2010]]>
            </date>
            <code>
                <![CDATA[ROE]]>
            </code>
            <is_promo>
                <![CDATA[false]]>
            </is_promo>
        </set>
        <set>
            <name>
                <![CDATA[Rivals of Ixalan]]>
            </name>
            <date>
                <![CDATA[01/2018]]>
            </date>
            <code>
                <![CDATA[RIX]]>
            </code>
            <is_promo>
                <![CDATA[false]]>
            </is_promo>
        </set>
        <set>
            <name>
                <![CDATA[Saviors of Kamigawa]]>
            </name>
            <date>
                <![CDATA[05/2005]]>
            </date>
            <code>
                <![CDATA[SOK]]>
            </code>
            <is_promo>
                <![CDATA[false]]>
            </is_promo>
        </set>
        <set>
            <name>
                <![CDATA[Scars of Mirrodin]]>
            </name>
            <date>
                <![CDATA[09/2010]]>
            </date>
            <code>
                <![CDATA[SOM]]>
            </code>
            <is_promo>
                <![CDATA[false]]>
            </is_promo>
        </set>
        <set>
            <name>
                <![CDATA[Scourge]]>
            </name>
            <date>
                <![CDATA[05/2003]]>
            </date>
            <code>
                <![CDATA[SCG]]>
            </code>
            <is_promo>
                <![CDATA[false]]>
            </is_promo>
        </set>
        <set>
            <name>
                <![CDATA[Seventh Edition]]>
            </name>
            <date>
                <![CDATA[04/2001]]>
            </date>
            <code>
                <![CDATA[7ED]]>
            </code>
            <is_promo>
                <![CDATA[false]]>
            </is_promo>
        </set>
        <set>
            <name>
                <![CDATA[Shadowmoor]]>
            </name>
            <date>
                <![CDATA[04/2008]]>
            </date>
            <code>
                <![CDATA[SHM]]>
            </code>
            <is_promo>
                <![CDATA[false]]>
            </is_promo>
        </set>
        <set>
            <name>
                <![CDATA[Shadows over Innistrad]]>
            </name>
            <date>
                <![CDATA[04/2016]]>
            </date>
            <code>
                <![CDATA[SOI]]>
            </code>
            <is_promo>
                <![CDATA[false]]>
            </is_promo>
        </set>
        <set>
            <name>
                <![CDATA[Shards of Alara]]>
            </name>
            <date>
                <![CDATA[09/2008]]>
            </date>
            <code>
                <![CDATA[ALA]]>
            </code>
            <is_promo>
                <![CDATA[false]]>
            </is_promo>
        </set>
        <set>
            <name>
                <![CDATA[Signature Spellbook: Jace]]>
            </name>
            <date>
                <![CDATA[06/2018]]>
            </date>
            <code>
                <![CDATA[SS1]]>
            </code>
            <is_promo>
                <![CDATA[true]]>
            </is_promo>
        </set>
        <set>
            <name>
                <![CDATA[Sixth Edition]]>
            </name>
            <date>
                <![CDATA[04/1999]]>
            </date>
            <code>
                <![CDATA[6ED]]>
            </code>
            <is_promo>
                <![CDATA[false]]>
            </is_promo>
        </set>
        <set>
            <name>
                <![CDATA[Starter 1999]]>
            </name>
            <date>
                <![CDATA[07/1999]]>
            </date>
            <code>
                <![CDATA[S99]]>
            </code>
            <is_promo>
                <![CDATA[true]]>
            </is_promo>
        </set>
        <set>
            <name>
                <![CDATA[Stronghold]]>
            </name>
            <date>
                <![CDATA[02/1998]]>
            </date>
            <code>
                <![CDATA[STH]]>
            </code>
            <is_promo>
                <![CDATA[false]]>
            </is_promo>
        </set>
        <set>
            <name>
                <![CDATA[Summer of Magic]]>
            </name>
            <date>
                <![CDATA[00/0000]]>
            </date>
            <code>
                <![CDATA[SUM]]>
            </code>
            <is_promo>
                <![CDATA[true]]>
            </is_promo>
        </set>
        <set>
            <name>
                <![CDATA[Super Series]]>
            </name>
            <date>
                <![CDATA[00/0000]]>
            </date>
            <code>
                <![CDATA[SUS]]>
            </code>
            <is_promo>
                <![CDATA[true]]>
            </is_promo>
        </set>
        <set>
            <name>
                <![CDATA[Tempest]]>
            </name>
            <date>
                <![CDATA[10/1997]]>
            </date>
            <code>
                <![CDATA[TMP]]>
            </code>
            <is_promo>
                <![CDATA[false]]>
            </is_promo>
        </set>
        <set>
            <name>
                <![CDATA[Tempest Remastered]]>
            </name>
            <date>
                <![CDATA[05/2015]]>
            </date>
            <code>
                <![CDATA[TPR]]>
            </code>
            <is_promo>
                <![CDATA[true]]>
            </is_promo>
        </set>
        <set>
            <name>
                <![CDATA[Tenth Edition]]>
            </name>
            <date>
                <![CDATA[07/2007]]>
            </date>
            <code>
                <![CDATA[10E]]>
            </code>
            <is_promo>
                <![CDATA[false]]>
            </is_promo>
        </set>
        <set>
            <name>
                <![CDATA[The Dark]]>
            </name>
            <date>
                <![CDATA[08/1994]]>
            </date>
            <code>
                <![CDATA[DRK]]>
            </code>
            <is_promo>
                <![CDATA[false]]>
            </is_promo>
        </set>
        <set>
            <name>
                <![CDATA[Theros]]>
            </name>
            <date>
                <![CDATA[09/2013]]>
            </date>
            <code>
                <![CDATA[THS]]>
            </code>
            <is_promo>
                <![CDATA[false]]>
            </is_promo>
        </set>
        <set>
            <name>
                <![CDATA[Third Edition Foreign Black Border]]>
            </name>
            <date>
                <![CDATA[04/1994]]>
            </date>
            <code>
                <![CDATA[FBB]]>
            </code>
            <is_promo>
                <![CDATA[false]]>
            </is_promo>
        </set>
        <set>
            <name>
                <![CDATA[Time Spiral]]>
            </name>
            <date>
                <![CDATA[09/2006]]>
            </date>
            <code>
                <![CDATA[TSP]]>
            </code>
            <is_promo>
                <![CDATA[false]]>
            </is_promo>
        </set>
        <set>
            <name>
                <![CDATA[Time Spiral "Timeshifted"]]>
            </name>
            <date>
                <![CDATA[09/2006]]>
            </date>
            <code>
                <![CDATA[TSB]]>
            </code>
            <is_promo>
                <![CDATA[false]]>
            </is_promo>
        </set>
        <set>
            <name>
                <![CDATA[Torment]]>
            </name>
            <date>
                <![CDATA[01/2002]]>
            </date>
            <code>
                <![CDATA[TOR]]>
            </code>
            <is_promo>
                <![CDATA[false]]>
            </is_promo>
        </set>
        <set>
            <name>
                <![CDATA[Two-Headed Giant Tournament]]>
            </name>
            <date>
                <![CDATA[00/0000]]>
            </date>
            <code>
                <![CDATA[2HG]]>
            </code>
            <is_promo>
                <![CDATA[true]]>
            </is_promo>
        </set>
        <set>
            <name>
                <![CDATA[Ugin's Fate Promos]]>
            </name>
            <date>
                <![CDATA[01/2015]]>
            </date>
            <code>
                <![CDATA[UGIN]]>
            </code>
            <is_promo>
                <![CDATA[true]]>
            </is_promo>
        </set>
        <set>
            <name>
                <![CDATA[Ultimate Box Toppers]]>
            </name>
            <date>
                <![CDATA[12/2008]]>
            </date>
            <code>
                <![CDATA[UBT]]>
            </code>
            <is_promo>
                <![CDATA[false]]>
            </is_promo>
        </set>
        <set>
            <name>
                <![CDATA[Ultimate Masters]]>
            </name>
            <date>
                <![CDATA[12/2008]]>
            </date>
            <code>
                <![CDATA[UMA]]>
            </code>
            <is_promo>
                <![CDATA[false]]>
            </is_promo>
        </set>
        <set>
            <name>
                <![CDATA[Unglued]]>
            </name>
            <date>
                <![CDATA[08/1998]]>
            </date>
            <code>
                <![CDATA[UGL]]>
            </code>
            <is_promo>
                <![CDATA[true]]>
            </is_promo>
        </set>
        <set>
            <name>
                <![CDATA[Unhinged]]>
            </name>
            <date>
                <![CDATA[11/2004]]>
            </date>
            <code>
                <![CDATA[UNH]]>
            </code>
            <is_promo>
                <![CDATA[true]]>
            </is_promo>
        </set>
        <set>
            <name>
                <![CDATA[Unlimited Edition]]>
            </name>
            <date>
                <![CDATA[12/1993]]>
            </date>
            <code>
                <![CDATA[2ED]]>
            </code>
            <is_promo>
                <![CDATA[false]]>
            </is_promo>
        </set>
        <set>
            <name>
                <![CDATA[Unstable]]>
            </name>
            <date>
                <![CDATA[12/2017]]>
            </date>
            <code>
                <![CDATA[UST]]>
            </code>
            <is_promo>
                <![CDATA[true]]>
            </is_promo>
        </set>
        <set>
            <name>
                <![CDATA[Urza's Destiny]]>
            </name>
            <date>
                <![CDATA[05/1999]]>
            </date>
            <code>
                <![CDATA[UDS]]>
            </code>
            <is_promo>
                <![CDATA[false]]>
            </is_promo>
        </set>
        <set>
            <name>
                <![CDATA[Urza's Legacy]]>
            </name>
            <date>
                <![CDATA[02/1999]]>
            </date>
            <code>
                <![CDATA[UDL]]>
            </code>
            <is_promo>
                <![CDATA[false]]>
            </is_promo>
        </set>
        <set>
            <name>
                <![CDATA[Urza's Saga]]>
            </name>
            <date>
                <![CDATA[10/1998]]>
            </date>
            <code>
                <![CDATA[USG]]>
            </code>
            <is_promo>
                <![CDATA[false]]>
            </is_promo>
        </set>
        <set>
            <name>
                <![CDATA[Vintage Championship]]>
            </name>
            <date>
                <![CDATA[00/0000]]>
            </date>
            <code>
                <![CDATA[OVNC]]>
            </code>
            <is_promo>
                <![CDATA[true]]>
            </is_promo>
        </set>
        <set>
            <name>
                <![CDATA[Vintage Masters]]>
            </name>
            <date>
                <![CDATA[06/2014]]>
            </date>
            <code>
                <![CDATA[VMA]]>
            </code>
            <is_promo>
                <![CDATA[true]]>
            </is_promo>
        </set>
        <set>
            <name>
                <![CDATA[Visions]]>
            </name>
            <date>
                <![CDATA[02/1997]]>
            </date>
            <code>
                <![CDATA[VIS]]>
            </code>
            <is_promo>
                <![CDATA[false]]>
            </is_promo>
        </set>
        <set>
            <name>
                <![CDATA[Weatherlight]]>
            </name>
            <date>
                <![CDATA[05/1997]]>
            </date>
            <code>
                <![CDATA[WTH]]>
            </code>
            <is_promo>
                <![CDATA[false]]>
            </is_promo>
        </set>
        <set>
            <name>
                <![CDATA[Welcome Deck 2016]]>
            </name>
            <date>
                <![CDATA[04/2016]]>
            </date>
            <code>
                <![CDATA[W16]]>
            </code>
            <is_promo>
                <![CDATA[true]]>
            </is_promo>
        </set>
        <set>
            <name>
                <![CDATA[Welcome Deck 2017]]>
            </name>
            <date>
                <![CDATA[04/2017]]>
            </date>
            <code>
                <![CDATA[W17]]>
            </code>
            <is_promo>
                <![CDATA[true]]>
            </is_promo>
        </set>
        <set>
            <name>
                <![CDATA[Wizards Play Network]]>
            </name>
            <date>
                <![CDATA[00/0000]]>
            </date>
            <code>
                <![CDATA[WPN]]>
            </code>
            <is_promo>
                <![CDATA[true]]>
            </is_promo>
        </set>
        <set>
            <name>
                <![CDATA[World Magic Cup Qualifiers]]>
            </name>
            <date>
                <![CDATA[00/0000]]>
            </date>
            <code>
                <![CDATA[WMC]]>
            </code>
            <is_promo>
                <![CDATA[true]]>
            </is_promo>
        </set>
        <set>
            <name>
                <![CDATA[Worlds]]>
            </name>
            <date>
                <![CDATA[00/0000]]>
            </date>
            <code>
                <![CDATA[WRL]]>
            </code>
            <is_promo>
                <![CDATA[true]]>
            </is_promo>
        </set>
        <set>
            <name>
                <![CDATA[Worldwake]]>
            </name>
            <date>
                <![CDATA[01/2010]]>
            </date>
            <code>
                <![CDATA[WWK]]>
            </code>
            <is_promo>
                <![CDATA[false]]>
            </is_promo>
        </set>
        <set>
            <name>
                <![CDATA[You make the Cube]]>
            </name>
            <date>
                <![CDATA[11/2016]]>
            </date>
            <code>
                <![CDATA[PZ2]]>
            </code>
            <is_promo>
                <![CDATA[true]]>
            </is_promo>
        </set>
        <set>
            <name>
                <![CDATA[Zendikar]]>
            </name>
            <date>
                <![CDATA[09/2009]]>
            </date>
            <code>
                <![CDATA[ZEN]]>
            </code>
            <is_promo>
                <![CDATA[false]]>
            </is_promo>
        </set>
    </sets>
</cardDataBase>
